jx_argparse/__init__.py
jx_argparse/command_line.py
jx_argparse/test.py
jx_argparse/resources/examples/argdef.json
jx_argparse/resources/examples/argdef.xml
jx_argparse/resources/examples/description_example.txt
jx_argparse-0.0.3.dev0.dist-info/LICENSE.rst
jx_argparse-0.0.3.dev0.dist-info/METADATA
jx_argparse-0.0.3.dev0.dist-info/WHEEL
jx_argparse-0.0.3.dev0.dist-info/entry_points.txt
jx_argparse-0.0.3.dev0.dist-info/top_level.txt
jx_argparse-0.0.3.dev0.dist-info/RECORD
